dioscuri/__init__.py
dioscuri/dioscuri.py
dioscuri-0.2.1.dist-info/licenses/LICENSE
tests/test_dioscuri.py
dioscuri-0.2.1.dist-info/METADATA
dioscuri-0.2.1.dist-info/WHEEL
dioscuri-0.2.1.dist-info/top_level.txt
dioscuri-0.2.1.dist-info/RECORD
