Metadata-Version: 2.4
Name: dioscuri
Version: 0.2.1
Summary: Read/write Gemini WorkList (gwl) files.
Author: Peter Vegh
License-Expression: MIT
Project-URL: Homepage, https://github.com/Edinburgh-Genome-Foundry/dioscuri
Keywords: biology
License-File: LICENSE
Requires-Dist: biopython
Dynamic: license-file
